README.md
license.txt
setup.py
Pnav.egg-info/PKG-INFO
Pnav.egg-info/SOURCES.txt
Pnav.egg-info/dependency_links.txt
Pnav.egg-info/top_level.txt
pnav/__init__.py
pnav/pnav.py
pnav.egg-info/PKG-INFO
pnav.egg-info/SOURCES.txt
pnav.egg-info/dependency_links.txt
pnav.egg-info/top_level.txt