Metadata-Version: 2.1
Name: pnav
Version: 0.2.7
Summary: Package with random functions, some are useful, some aren't so much. They are however used often, maintained, and good for learning.
Home-page: https://pypi.org/project/pnav/
Author: Zander Navratil
License: UNKNOWN
Platform: UNKNOWN
License-File: license.txt
